<?xml version="1.0" encoding="utf-8"?>
<tv>
  <channel id="ONE">
    <display-name lang="th">ONE 31 HD</display-name>
    <icon src="..."/>
  </channel>
  <channel id="Thairath">
    <display-name lang="th">Thairath TV</display-name>
    <icon src="..."/>
  </channel>
  <channel id="MONO29">
    <display-name lang="th">MONO29 HD</display-name>
    <icon src="..."/>
  </channel>
  <channel id="3HD">
    <display-name lang="th">3 HD</display-name>
    <icon src="..."/>
  </channel>
  <channel id="Amarin">
    <display-name lang="th">Amarin TV HD</display-name>
    <icon src="..."/>
  </channel>
  <channel id="7HD">
    <display-name lang="th">7 HD</display-name>
    <icon src="..."/>
  </channel>
  <channel id="Workpoint">
    <display-name lang="th">Workpoint HD</display-name>
    <icon src="..."/>
  </channel>
  <channel id="PPTV">
    <display-name lang="th">PPTV HD</display-name>
    <icon src="..."/>
  </channel>
  <channel id="True24">
    <display-name lang="th">True24 SD</display-name>
    <icon src="..."/>
  </channel>
  <channel id="GMM25">
    <display-name lang="th">GMM 25</display-name>
    <icon src="..."/>
  </channel>
  <channel id="TOPNew">
    <display-name lang="th">TOP New SD</display-name>
    <icon src="..."/>
  </channel>
  <channel id="TPBS">
    <display-name lang="th">TPBS HD</display-name>
    <icon src="..."/>
  </channel>
  <channel id="8SD">
    <display-name lang="th">ช่อง 8 SD</display-name>
    <icon src="..."/>
  </channel>
  <channel id="Nation">
    <display-name lang="th">Nation HD</display-name>
    <icon src="..."/>
  </channel>
  <channel id="Boomerang">
    <display-name lang="th">Boomerang</display-name>
    <icon src="..."/>
  </channel>
  <channel id="MCOT">
    <display-name lang="th">MCOT HD</display-name>
    <icon src="..."/>
  </channel>
  <channel id="TNN">
    <display-name lang="th">TNN SD</display-name>
    <icon src="..."/>
  </channel>
  <channel id="5HD">
    <display-name lang="th">5HD</display-name>
    <icon src="..."/>
  </channel>
  <channel id="JKN18">
    <display-name lang="th">JKN18</display-name>
    <icon src="..."/>
  </channel>
  <channel id="NBT">
    <display-name lang="th">NBT</display-name>
    <icon src="..."/>
  </channel>
  <channel id="ALTV">
    <display-name lang="th">ALTV</display-name>
    <icon src="..."/>
  </channel>
  <programme start="20251016025500 +0700" stop="20251016034500 +0700" channel="ONE">
    <title lang="th">(RERUN) เฮง เฮง เฮง</title>
    <desc lang="th">-</desc>
  </programme>
  <programme start="20251016034500 +0700" stop="20251016044500 +0700" channel="ONE">
    <title lang="th">(RERUN) เอาให้ชัด</title>
    <desc lang="th">-</desc>
  </programme>
  <programme start="20251016044500 +0700" stop="20251016060000 +0700" channel="ONE">
    <title lang="th">(RERUN) ดวลเพลงชิงทุน</title>
    <desc lang="th">-</desc>
  </programme>
  <programme start="20251016060000 +0700" stop="20251016080600 +0700" channel="ONE">
    <title lang="th">ข่าวเช้าช่องวัน</title>
    <desc lang="th">-</desc>
  </programme>
  <programme start="20251016080600 +0700" stop="20251016115000 +0700" channel="ONE">
    <title lang="th">หีบหลอนซ่อนวิญญาณ</title>
    <desc lang="th">-</desc>
  </programme>
  <programme start="20251016115000 +0700" stop="20251016123000 +0700" channel="ONE">
    <title lang="th">รอบวัน</title>
    <desc lang="th">-</desc>
  </programme>
  <programme start="20251016123000 +0700" stop="20251016133000 +0700" channel="ONE">
    <title lang="th">เรื่องใหญ่รายวัน</title>
    <desc lang="th">-</desc>
  </programme>
  <programme start="20251016133000 +0700" stop="20251016140500 +0700" channel="ONE">
    <title lang="th">อนุวัตทั่วไทย</title>
    <desc lang="th">-</desc>
  </programme>
  <programme start="20251016140500 +0700" stop="20251016162000 +0700" channel="ONE">
    <title lang="th">วิวาห์ฟ้าแลบ</title>
    <desc lang="th">-</desc>
  </programme>
  <programme start="20251016162000 +0700" stop="20251016180000 +0700" channel="ONE">
    <title lang="th">ข่าวเย็นช่องวัน</title>
    <desc lang="th">-</desc>
  </programme>
  <programme start="20251016180000 +0700" stop="20251016190000 +0700" channel="ONE">
    <title lang="th">ดวลเพลงชิงทุน</title>
    <desc lang="th">-</desc>
  </programme>
  <programme start="20251016190000 +0700" stop="20251016200000 +0700" channel="ONE">
    <title lang="th">สงครามหมอลำ</title>
    <desc lang="th">-</desc>
  </programme>
  <programme start="20251016200000 +0700" stop="20251016200000 +0700" channel="ONE">
    <title lang="th">ข่าวค่ำช่องวัน และ ข่าวในพระราชสำนัก</title>
    <desc lang="th">-</desc>
  </programme>
  <programme start="20251016200000 +0700" stop="20251016203000 +0700" channel="ONE">
    <title lang="th">ข่าวค่ำช่องวัน  ช่วงที่สอง</title>
    <desc lang="th">-</desc>
  </programme>
  <programme start="20251016203000 +0700" stop="20251016213000 +0700" channel="ONE">
    <title lang="th">ทายาทหมายเลข 1</title>
    <desc lang="th">-</desc>
  </programme>
  <programme start="20251016213000 +0700" stop="20251016223000 +0700" channel="ONE">
    <title lang="th">เอาให้ชัด</title>
    <desc lang="th">-</desc>
  </programme>
  <programme start="20251016223000 +0700" stop="20251016235900 +0700" channel="ONE">
    <title lang="th">เป็นต่อ</title>
    <desc lang="th">-</desc>
  </programme>
  <programme start="20251016000000 +0700" stop="20251016011500 +0700" channel="Thairath">
    <title lang="th">ข่าวใส่ไข่ (Rerun)</title>
    <desc lang="th">-</desc>
  </programme>
  <programme start="20251016011500 +0700" stop="20251016023500 +0700" channel="Thairath">
    <title lang="th">ตะลอนข่าว (Rerun)</title>
    <desc lang="th">-</desc>
  </programme>
  <programme start="20251016023500 +0700" stop="20251016033500 +0700" channel="Thairath">
    <title lang="th">ข่าวแสบเฉพาะกิจ AD CC</title>
    <desc lang="th">-</desc>
  </programme>
  <programme start="20251016033500 +0700" stop="20251016042900 +0700" channel="Thairath">
    <title lang="th">คู่กัดสะบัดข่าว (Rerun)</title>
    <desc lang="th">-</desc>
  </programme>
  <programme start="20251016042900 +0700" stop="20251016045900 +0700" channel="Thairath">
    <title lang="th">True Shopping 04.30</title>
    <desc lang="th">-</desc>
  </programme>
  <programme start="20251016045900 +0700" stop="20251016050000 +0700" channel="Thairath">
    <title lang="th">เพลง สรรเสริญพระบารมี รัชกาลที่ 10</title>
    <desc lang="th">-</desc>
  </programme>
  <programme start="20251016050000 +0700" stop="20251016053000 +0700" channel="Thairath">
    <title lang="th">True Shopping 05.00-05.30</title>
    <desc lang="th">-</desc>
  </programme>
  <programme start="20251016053000 +0700" stop="20251016063000 +0700" channel="Thairath">
    <title lang="th">ห้องข่าว หัวเขียว</title>
    <desc lang="th">-</desc>
  </programme>
  <programme start="20251016063000 +0700" stop="20251016080000 +0700" channel="Thairath">
    <title lang="th">ข่าวเช้าหัวเขียว</title>
    <desc lang="th">-</desc>
  </programme>
  <programme start="20251016080000 +0700" stop="20251016083000 +0700" channel="Thairath">
    <title lang="th">เพลงชาติไทย v.cc</title>
    <desc lang="th">-</desc>
  </programme>
  <programme start="20251016083000 +0700" stop="20251016095300 +0700" channel="Thairath">
    <title lang="th">ตะลอนข่าว</title>
    <desc lang="th">-</desc>
  </programme>
  <programme start="20251016095300 +0700" stop="20251016095800 +0700" channel="Thairath">
    <title lang="th">O Shopping</title>
    <desc lang="th">-</desc>
  </programme>
  <programme start="20251016095800 +0700" stop="20251016100000 +0700" channel="Thairath">
    <title lang="th">Express News</title>
    <desc lang="th">-</desc>
  </programme>
  <programme start="20251016100000 +0700" stop="20251016105800 +0700" channel="Thairath">
    <title lang="th">ปูเสื่อรอ</title>
    <desc lang="th">-</desc>
  </programme>
  <programme start="20251016105800 +0700" stop="20251016110000 +0700" channel="Thairath">
    <title lang="th">Express News</title>
    <desc lang="th">-</desc>
  </programme>
  <programme start="20251016110000 +0700" stop="20251016114500 +0700" channel="Thairath">
    <title lang="th">ข่าวเที่ยงไทยรัฐ ช่วงที่ 1</title>
    <desc lang="th">-</desc>
  </programme>
  <programme start="20251016114500 +0700" stop="20251016132800 +0700" channel="Thairath">
    <title lang="th">ข่าวเที่ยงไทยรัฐ</title>
    <desc lang="th">-</desc>
  </programme>
  <programme start="20251016132800 +0700" stop="20251016133000 +0700" channel="Thairath">
    <title lang="th">Express News</title>
    <desc lang="th">-</desc>
  </programme>
  <programme start="20251016133000 +0700" stop="20251016142800 +0700" channel="Thairath">
    <title lang="th">บันเทิงไทยรัฐ (บ่าย)</title>
    <desc lang="th">-</desc>
  </programme>
  <programme start="20251016142800 +0700" stop="20251016143000 +0700" channel="Thairath">
    <title lang="th">Express News</title>
    <desc lang="th">-</desc>
  </programme>
  <programme start="20251016143000 +0700" stop="20251016152800 +0700" channel="Thairath">
    <title lang="th">คู่กัดสะบัดข่าว</title>
    <desc lang="th">-</desc>
  </programme>
  <programme start="20251016152800 +0700" stop="20251016153000 +0700" channel="Thairath">
    <title lang="th">Express News</title>
    <desc lang="th">-</desc>
  </programme>
  <programme start="20251016153000 +0700" stop="20251016161500 +0700" channel="Thairath">
    <title lang="th">เปิดปากกับภาคภูมิ</title>
    <desc lang="th">-</desc>
  </programme>
  <programme start="20251016161500 +0700" stop="20251016162000 +0700" channel="Thairath">
    <title lang="th">หั่นราคา ท้าช็อป 16.15</title>
    <desc lang="th">-</desc>
  </programme>
  <programme start="20251016162000 +0700" stop="20251016174500 +0700" channel="Thairath">
    <title lang="th">ข่าวเย็นไทยรัฐ</title>
    <desc lang="th">-</desc>
  </programme>
  <programme start="20251016174500 +0700" stop="20251016180000 +0700" channel="Thairath">
    <title lang="th">ข่าวใส่ไข่</title>
    <desc lang="th">-</desc>
  </programme>
  <programme start="20251016180000 +0700" stop="20251016190000 +0700" channel="Thairath">
    <title lang="th">เพลงชาติไทย v.cc</title>
    <desc lang="th">-</desc>
  </programme>
  <programme start="20251016190000 +0700" stop="20251016200000 +0700" channel="Thairath">
    <title lang="th">ไทยรัฐ นิวส์โชว์ ช่วง 1</title>
    <desc lang="th">-</desc>
  </programme>
  <programme start="20251016200000 +0700" stop="20251016201500 +0700" channel="Thairath">
    <title lang="th">ข่าวในพระราชสำนัก</title>
    <desc lang="th">-</desc>
  </programme>
  <programme start="20251016201500 +0700" stop="20251016222800 +0700" channel="Thairath">
    <title lang="th">ไทยรัฐ นิวส์โชว์</title>
    <desc lang="th">-</desc>
  </programme>
  <programme start="20251016222800 +0700" stop="20251016223000 +0700" channel="Thairath">
    <title lang="th">Express News</title>
    <desc lang="th">-</desc>
  </programme>
  <programme start="20251016223000 +0700" stop="20251016223500 +0700" channel="Thairath">
    <title lang="th">หั่นราคา ท้าช็อป 22.40</title>
    <desc lang="th">-</desc>
  </programme>
  <programme start="20251016223500 +0700" stop="20251016232000 +0700" channel="Thairath">
    <title lang="th">เปิดปากกับภาคภูมิ (Rerun)</title>
    <desc lang="th">-</desc>
  </programme>
  <programme start="20251016232000 +0700" stop="20251016235900 +0700" channel="Thairath">
    <title lang="th">ไทยรัฐเจาะประเด็น</title>
    <desc lang="th">-</desc>
  </programme>
  <programme start="20251016033000 +0700" stop="20251016070000 +0700" channel="MONO29">
    <title lang="th">World Voyage โลกเดินเรื่อง</title>
    <desc lang="th">-</desc>
  </programme>
  <programme start="20251016070000 +0700" stop="20251016080000 +0700" channel="MONO29">
    <title lang="th">ข่าวเด็ด : MONO ข่าวเช้า</title>
    <desc lang="th">-</desc>
  </programme>
  <programme start="20251016080000 +0700" stop="20251016090000 +0700" channel="MONO29">
    <title lang="th">ซีรีส์ : กระจกสองนครา Mirror: A Tale of Twin Cities (EP.14)</title>
    <desc lang="th">-</desc>
  </programme>
  <programme start="20251016090000 +0700" stop="20251016091000 +0700" channel="MONO29">
    <title lang="th">ข่าวเด็ด : What's up 29</title>
    <desc lang="th">-</desc>
  </programme>
  <programme start="20251016091000 +0700" stop="20251016094500 +0700" channel="MONO29">
    <title lang="th">ข่าวเด็ด : โฟกัส เศรษฐกิจ</title>
    <desc lang="th">-</desc>
  </programme>
  <programme start="20251016094500 +0700" stop="20251016120500 +0700" channel="MONO29">
    <title lang="th">ภาพยนตร์ : The Green Hornet หน้ากากแตนอาละวาด</title>
    <desc lang="th">-</desc>
  </programme>
  <programme start="20251016120500 +0700" stop="20251016142000 +0700" channel="MONO29">
    <title lang="th">ภาพยนตร์ : Cloudy Mountain กู้ปฐพีเดือด</title>
    <desc lang="th">-</desc>
  </programme>
  <programme start="20251016142000 +0700" stop="20251016150500 +0700" channel="MONO29">
    <title lang="th">ข่าวเด็ด : MONO เจาะข่าวเด็ด</title>
    <desc lang="th">-</desc>
  </programme>
  <programme start="20251016150500 +0700" stop="20251016170000 +0700" channel="MONO29">
    <title lang="th">ภาพยนตร์ : Today You Die ยุทธการปล้นเฉียดนรก</title>
    <desc lang="th">-</desc>
  </programme>
  <programme start="20251016170000 +0700" stop="20251016180000 +0700" channel="MONO29">
    <title lang="th">ข่าวเด็ด : ข่าวพร้อมบวก</title>
    <desc lang="th">-</desc>
  </programme>
  <programme start="20251016180000 +0700" stop="20251016195500 +0700" channel="MONO29">
    <title lang="th">ภาพยนตร์ : The Lost City ผจญภัยนครสาบสูญ</title>
    <desc lang="th">-</desc>
  </programme>
  <programme start="20251016195500 +0700" stop="20251016201500 +0700" channel="MONO29">
    <title lang="th">ข่าวเด็ด : MONO ข่าวค่ำ</title>
    <desc lang="th">-</desc>
  </programme>
  <programme start="20251016201500 +0700" stop="20251016210000 +0700" channel="MONO29">
    <title lang="th">ข่าวเด็ด : ข่าวในพระราชสำนัก</title>
    <desc lang="th">-</desc>
  </programme>
  <programme start="20251016210000 +0700" stop="20251016220000 +0700" channel="MONO29">
    <title lang="th">ซีรีส์ : บุปผารักคืนใจ In Blossom (EP.10)</title>
    <desc lang="th">-</desc>
  </programme>
  <programme start="20251016220000 +0700" stop="20251016224500 +0700" channel="MONO29">
    <title lang="th">ข่าวเด็ด : ชัดทุกข่าว</title>
    <desc lang="th">-</desc>
  </programme>
  <programme start="20251016224500 +0700" stop="20251016231500 +0700" channel="MONO29">
    <title lang="th">KICK IT REAL</title>
    <desc lang="th">-</desc>
  </programme>
  <programme start="20251016231500 +0700" stop="20251016232000 +0700" channel="MONO29">
    <title lang="th">Premier League Highlights</title>
    <desc lang="th">-</desc>
  </programme>
  <programme start="20251016232000 +0700" stop="20251016235900 +0700" channel="MONO29">
    <title lang="th">รายการทั่วไป : Luxury 29</title>
    <desc lang="th">-</desc>
  </programme>
  <programme start="20251016035000 +0700" stop="20251016040000 +0700" channel="3HD">
    <title lang="th">โอช้อปปิ้ง</title>
    <desc lang="th">-</desc>
  </programme>
  <programme start="20251016040000 +0700" stop="20251016045000 +0700" channel="3HD">
    <title lang="th">ย้อนเวลาหาละคร เสน่ห์นางงิ้ว</title>
    <desc lang="th">-</desc>
  </programme>
  <programme start="20251016045000 +0700" stop="20251016045500 +0700" channel="3HD">
    <title lang="th">ตะวันส่องธรรม</title>
    <desc lang="th">-</desc>
  </programme>
  <programme start="20251016045500 +0700" stop="20251016052300 +0700" channel="3HD">
    <title lang="th">ขันข่าวเช้าตรู่</title>
    <desc lang="th">-</desc>
  </programme>
  <programme start="20251016052300 +0700" stop="20251016053000 +0700" channel="3HD">
    <title lang="th">Happy Shopping</title>
    <desc lang="th">-</desc>
  </programme>
  <programme start="20251016053000 +0700" stop="20251016060000 +0700" channel="3HD">
    <title lang="th">เรื่องเล่าหน้าหนึ่ง</title>
    <desc lang="th">-</desc>
  </programme>
  <programme start="20251016060000 +0700" stop="20251016082000 +0700" channel="3HD">
    <title lang="th">เรื่องเล่าเช้านี้</title>
    <desc lang="th">-</desc>
  </programme>
  <programme start="20251016082000 +0700" stop="20251016082500 +0700" channel="3HD">
    <title lang="th">เพื่อนคู่คิด</title>
    <desc lang="th">-</desc>
  </programme>
  <programme start="20251016082500 +0700" stop="20251016084500 +0700" channel="3HD">
    <title lang="th">ผู้หญิงยกกำลังเเจ๋ว</title>
    <desc lang="th">-</desc>
  </programme>
  <programme start="20251016084500 +0700" stop="20251016085000 +0700" channel="3HD">
    <title lang="th">อร่อยเลิศกับคุณหรีด</title>
    <desc lang="th">-</desc>
  </programme>
  <programme start="20251016085000 +0700" stop="20251016085500 +0700" channel="3HD">
    <title lang="th">5 นาที โปรฯดี โอจัดให้</title>
    <desc lang="th">-</desc>
  </programme>
  <programme start="20251016085500 +0700" stop="20251016102500 +0700" channel="3HD">
    <title lang="th">ละครดังข้ามเวลา เล่ห์ลับสลับร่าง</title>
    <desc lang="th">-</desc>
  </programme>
  <programme start="20251016102500 +0700" stop="20251016105000 +0700" channel="3HD">
    <title lang="th">ทีเด็ดลูกหนี้</title>
    <desc lang="th">-</desc>
  </programme>
  <programme start="20251016105000 +0700" stop="20251016105500 +0700" channel="3HD">
    <title lang="th">Happy Shopping</title>
    <desc lang="th">-</desc>
  </programme>
  <programme start="20251016105500 +0700" stop="20251016112000 +0700" channel="3HD">
    <title lang="th">ฮาเกินต้าน</title>
    <desc lang="th">-</desc>
  </programme>
  <programme start="20251016112000 +0700" stop="20251016123000 +0700" channel="3HD">
    <title lang="th">เที่ยงวันทันเหตุการณ์</title>
    <desc lang="th">-</desc>
  </programme>
  <programme start="20251016123000 +0700" stop="20251016132500 +0700" channel="3HD">
    <title lang="th">โหนกระเเส</title>
    <desc lang="th">-</desc>
  </programme>
  <programme start="20251016132500 +0700" stop="20251016133000 +0700" channel="3HD">
    <title lang="th">บางกอกกระซิบ โว้ว มายา</title>
    <desc lang="th">-</desc>
  </programme>
  <programme start="20251016133000 +0700" stop="20251016140000 +0700" channel="3HD">
    <title lang="th">ครัวคุณต๋อย</title>
    <desc lang="th">-</desc>
  </programme>
  <programme start="20251016140000 +0700" stop="20251016140700 +0700" channel="3HD">
    <title lang="th">Happy Shopping</title>
    <desc lang="th">-</desc>
  </programme>
  <programme start="20251016140700 +0700" stop="20251016143700 +0700" channel="3HD">
    <title lang="th">ข่าว 3 สี</title>
    <desc lang="th">-</desc>
  </programme>
  <programme start="20251016143700 +0700" stop="20251016163000 +0700" channel="3HD">
    <title lang="th">ละคร เลือดมังกร: เสือ/ โอ ช้อปปิ้ง /ละคร</title>
    <desc lang="th">-</desc>
  </programme>
  <programme start="20251016163000 +0700" stop="20251016175900 +0700" channel="3HD">
    <title lang="th">เรื่องเด่นเย็นนี้</title>
    <desc lang="th">-</desc>
  </programme>
  <programme start="20251016175900 +0700" stop="20251016180000 +0700" channel="3HD">
    <title lang="th">อิงลิช ออน ทัวร์</title>
    <desc lang="th">-</desc>
  </programme>
  <programme start="20251016180000 +0700" stop="20251016190000 +0700" channel="3HD">
    <title lang="th">ละคร สุภาพบุรุษจุฑาเทพ คุณชายรณพีร์</title>
    <desc lang="th">-</desc>
  </programme>
  <programme start="20251016190000 +0700" stop="20251016200000 +0700" channel="3HD">
    <title lang="th">ละคร กรงดอกสร้อย</title>
    <desc lang="th">-</desc>
  </programme>
  <programme start="20251016200000 +0700" stop="20251016201500 +0700" channel="3HD">
    <title lang="th">ข่าวนอกลู่</title>
    <desc lang="th">-</desc>
  </programme>
  <programme start="20251016201500 +0700" stop="20251016203000 +0700" channel="3HD">
    <title lang="th">ข่าวในพระราชสำนัก / สีสันบันเทิง</title>
    <desc lang="th">-</desc>
  </programme>
  <programme start="20251016203000 +0700" stop="20251016214500 +0700" channel="3HD">
    <title lang="th">ละคร เจ้าคุณพี่กับอีนางคำดวง</title>
    <desc lang="th">-</desc>
  </programme>
  <programme start="20251016214500 +0700" stop="20251016223000 +0700" channel="3HD">
    <title lang="th">ข่าว 3 มิติ</title>
    <desc lang="th">-</desc>
  </programme>
  <programme start="20251016223000 +0700" stop="20251016233000 +0700" channel="3HD">
    <title lang="th">ซีรีส์ รับ (รัก) ออกแบบ Love Design</title>
    <desc lang="th">-</desc>
  </programme>
  <programme start="20251016233000 +0700" stop="20251016235900 +0700" channel="3HD">
    <title lang="th">แก้เกมเศรษฐกิจ / ของฝากนักกอล์ฟ</title>
    <desc lang="th">-</desc>
  </programme>
  <programme start="20251016023000 +0700" stop="20251016030000 +0700" channel="Amarin">
    <title lang="th">ชีวิตดีดี มีได้ทุกวัน</title>
    <desc lang="th">-</desc>
  </programme>
  <programme start="20251016030000 +0700" stop="20251016033000 +0700" channel="Amarin">
    <title lang="th">เรื่องเด็ดเอ็ดตะโร</title>
    <desc lang="th">-</desc>
  </programme>
  <programme start="20251016033000 +0700" stop="20251016040000 +0700" channel="Amarin">
    <title lang="th">โปรดีคนตื่นเช้า</title>
    <desc lang="th">-</desc>
  </programme>
  <programme start="20251016040000 +0700" stop="20251016043000 +0700" channel="Amarin">
    <title lang="th">Happy Shopping</title>
    <desc lang="th">-</desc>
  </programme>
  <programme start="20251016043000 +0700" stop="20251016053000 +0700" channel="Amarin">
    <title lang="th">สุขทุกวัน 7 วัน 7 กูรู</title>
    <desc lang="th">-</desc>
  </programme>
  <programme start="20251016053000 +0700" stop="20251016063000 +0700" channel="Amarin">
    <title lang="th">ข่าวอรุณอมรินทร์ ทั่วไทย</title>
    <desc lang="th">-</desc>
  </programme>
  <programme start="20251016063000 +0700" stop="20251016080000 +0700" channel="Amarin">
    <title lang="th">ข่าวอรุณอมรินทร์</title>
    <desc lang="th">-</desc>
  </programme>
  <programme start="20251016080000 +0700" stop="20251016080100 +0700" channel="Amarin">
    <title lang="th">เพลงชาติไทย</title>
    <desc lang="th">-</desc>
  </programme>
  <programme start="20251016080100 +0700" stop="20251016084500 +0700" channel="Amarin">
    <title lang="th">ข่าวอรุณอมรินทร์</title>
    <desc lang="th">-</desc>
  </programme>
  <programme start="20251016084500 +0700" stop="20251016090500 +0700" channel="Amarin">
    <title lang="th">Sport Lifestyle 34</title>
    <desc lang="th">-</desc>
  </programme>
  <programme start="20251016090500 +0700" stop="20251016091500 +0700" channel="Amarin">
    <title lang="th">ดีลดีไดเร็ค</title>
    <desc lang="th">-</desc>
  </programme>
  <programme start="20251016091500 +0700" stop="20251016093000 +0700" channel="Amarin">
    <title lang="th">เรื่องเด็ดเอ็ดตะโร รีรัน</title>
    <desc lang="th">-</desc>
  </programme>
  <programme start="20251016093000 +0700" stop="20251016095000 +0700" channel="Amarin">
    <title lang="th">Car On TV</title>
    <desc lang="th">-</desc>
  </programme>
  <programme start="20251016095000 +0700" stop="20251016100000 +0700" channel="Amarin">
    <title lang="th">ดีลดีไดเร็ค</title>
    <desc lang="th">-</desc>
  </programme>
  <programme start="20251016100000 +0700" stop="20251016103000 +0700" channel="Amarin">
    <title lang="th">ชีพจรลงพุง รีรัน</title>
    <desc lang="th">-</desc>
  </programme>
  <programme start="20251016103000 +0700" stop="20251016110000 +0700" channel="Amarin">
    <title lang="th">ตามอำเภอจาน รีรัน</title>
    <desc lang="th">-</desc>
  </programme>
  <programme start="20251016110000 +0700" stop="20251016134000 +0700" channel="Amarin">
    <title lang="th">ข่าวเที่ยงอมรินทร์</title>
    <desc lang="th">-</desc>
  </programme>
  <programme start="20251016134000 +0700" stop="20251016135000 +0700" channel="Amarin">
    <title lang="th">ดีลดีไดเร็ค</title>
    <desc lang="th">-</desc>
  </programme>
  <programme start="20251016135000 +0700" stop="20251016160000 +0700" channel="Amarin">
    <title lang="th">ถ่ายทอดสดผลการออกรางวัลสลากกินแบ่งรัฐบาล</title>
    <desc lang="th">-</desc>
  </programme>
  <programme start="20251016160000 +0700" stop="20251016170000 +0700" channel="Amarin">
    <title lang="th">ข่าวเย็นอมรินทร์</title>
    <desc lang="th">-</desc>
  </programme>
  <programme start="20251016170000 +0700" stop="20251016180000 +0700" channel="Amarin">
    <title lang="th">ฅ.คนขั้นเทพ</title>
    <desc lang="th">-</desc>
  </programme>
  <programme start="20251016180000 +0700" stop="20251016180100 +0700" channel="Amarin">
    <title lang="th">เพลงชาติไทย</title>
    <desc lang="th">-</desc>
  </programme>
  <programme start="20251016180100 +0700" stop="20251016185500 +0700" channel="Amarin">
    <title lang="th">ตามอำเภอจาน รวมฮิต</title>
    <desc lang="th">-</desc>
  </programme>
  <programme start="20251016185500 +0700" stop="20251016200000 +0700" channel="Amarin">
    <title lang="th">ทุบโต๊ะข่าว</title>
    <desc lang="th">-</desc>
  </programme>
  <programme start="20251016200000 +0700" stop="20251016201500 +0700" channel="Amarin">
    <title lang="th">ข่าวในพระราชสำนัก</title>
    <desc lang="th">-</desc>
  </programme>
  <programme start="20251016201500 +0700" stop="20251016220000 +0700" channel="Amarin">
    <title lang="th">ทุบโต๊ะข่าว</title>
    <desc lang="th">-</desc>
  </programme>
  <programme start="20251016220000 +0700" stop="20251016223000 +0700" channel="Amarin">
    <title lang="th">ทุบโต๊ะข่าว X'Clusive</title>
    <desc lang="th">-</desc>
  </programme>
  <programme start="20251016223000 +0700" stop="20251016223700 +0700" channel="Amarin">
    <title lang="th">โปรดี คนนอนดึก</title>
    <desc lang="th">-</desc>
  </programme>
  <programme start="20251016223700 +0700" stop="20251016230000 +0700" channel="Amarin">
    <title lang="th">เซเลบริตี้ มอลล์</title>
    <desc lang="th">-</desc>
  </programme>
  <programme start="20251016230000 +0700" stop="20251016232000 +0700" channel="Amarin">
    <title lang="th">Auto World</title>
    <desc lang="th">-</desc>
  </programme>
  <programme start="20251016232000 +0700" stop="20251016233500 +0700" channel="Amarin">
    <title lang="th">ชีพจรลงพุงไกด์</title>
    <desc lang="th">-</desc>
  </programme>
  <programme start="20251016233500 +0700" stop="20251016235900 +0700" channel="Amarin">
    <title lang="th">Tel2Tell TV Shopping</title>
    <desc lang="th">-</desc>
  </programme>
  <programme start="20251016023000 +0700" stop="20251016033000 +0700" channel="True24">
    <title lang="th">TNN ข่าวเที่ยง 2025</title>
    <desc lang="th">-</desc>
  </programme>
  <programme start="20251016033000 +0700" stop="20251016043000 +0700" channel="True24">
    <title lang="th">สามเณรปลูกปัญญาธรรม ปี4</title>
    <desc lang="th">-</desc>
  </programme>
  <programme start="20251016043000 +0700" stop="20251016050000 +0700" channel="True24">
    <title lang="th">เรื่องดีดีทั่วไทย 2025</title>
    <desc lang="th">-</desc>
  </programme>
  <programme start="20251016050000 +0700" stop="20251016060000 +0700" channel="True24">
    <title lang="th">I Need Romance รักใช่ไหมที่หัวใจต้องการ</title>
    <desc lang="th">-</desc>
  </programme>
  <programme start="20251016060000 +0700" stop="20251016070000 +0700" channel="True24">
    <title lang="th">รักแรกของฉันกับคดีพิลึกพิลั่นของเจ้าบ่าว</title>
    <desc lang="th">-</desc>
  </programme>
  <programme start="20251016070000 +0700" stop="20251016080000 +0700" channel="True24">
    <title lang="th">สามเณรปลูกปัญญาธรรม ปี4</title>
    <desc lang="th">-</desc>
  </programme>
  <programme start="20251016080000 +0700" stop="20251016080100 +0700" channel="True24">
    <title lang="th">เพลงชาติไทย</title>
    <desc lang="th">-</desc>
  </programme>
  <programme start="20251016080100 +0700" stop="20251016083000 +0700" channel="True24">
    <title lang="th">ทรูช้อปปิ้ง</title>
    <desc lang="th">-</desc>
  </programme>
  <programme start="20251016083000 +0700" stop="20251016102500 +0700" channel="True24">
    <title lang="th">ภาพยนตร์ สารวัตรหมาบ้า</title>
    <desc lang="th">-</desc>
  </programme>
  <programme start="20251016102500 +0700" stop="20251016105500 +0700" channel="True24">
    <title lang="th">ทรูช้อปปิ้ง</title>
    <desc lang="th">-</desc>
  </programme>
  <programme start="20251016105500 +0700" stop="20251016112500 +0700" channel="True24">
    <title lang="th">เรื่องดีดีทั่วไทย 2025</title>
    <desc lang="th">-</desc>
  </programme>
  <programme start="20251016112500 +0700" stop="20251016113000 +0700" channel="True24">
    <title lang="th">Happy Shopping</title>
    <desc lang="th">-</desc>
  </programme>
  <programme start="20251016113000 +0700" stop="20251016123000 +0700" channel="True24">
    <title lang="th">TNN ข่าวเที่ยง 2025</title>
    <desc lang="th">-</desc>
  </programme>
  <programme start="20251016123000 +0700" stop="20251016143000 +0700" channel="True24">
    <title lang="th">ภาพยนตร์ คู่หูขวางนรก ตลอดกาล</title>
    <desc lang="th">-</desc>
  </programme>
  <programme start="20251016143000 +0700" stop="20251016150000 +0700" channel="True24">
    <title lang="th">ทรูช้อปปิ้ง</title>
    <desc lang="th">-</desc>
  </programme>
  <programme start="20251016150000 +0700" stop="20251016170000 +0700" channel="True24">
    <title lang="th">ภาพยนตร์ 18 ผู้กล้าเสี้ยวลิ้มยี้</title>
    <desc lang="th">-</desc>
  </programme>
  <programme start="20251016170000 +0700" stop="20251016175500 +0700" channel="True24">
    <title lang="th">Match Day</title>
    <desc lang="th">-</desc>
  </programme>
  <programme start="20251016175500 +0700" stop="20251016180000 +0700" channel="True24">
    <title lang="th">Happy Shopping</title>
    <desc lang="th">-</desc>
  </programme>
  <programme start="20251016180000 +0700" stop="20251016180100 +0700" channel="True24">
    <title lang="th">เพลงชาติไทย</title>
    <desc lang="th">-</desc>
  </programme>
  <programme start="20251016180100 +0700" stop="20251016201000 +0700" channel="True24">
    <title lang="th">ศึกเพชรยินดี 2025</title>
    <desc lang="th">-</desc>
  </programme>
  <programme start="20251016201000 +0700" stop="20251016204000 +0700" channel="True24">
    <title lang="th">ข่าวในพระราชสำนัก</title>
    <desc lang="th">-</desc>
  </programme>
  <programme start="20251016204000 +0700" stop="20251016224500 +0700" channel="True24">
    <title lang="th">ภาพยนตร์ ซุ้มมือปืน</title>
    <desc lang="th">-</desc>
  </programme>
  <programme start="20251016224500 +0700" stop="20251016235900 +0700" channel="True24">
    <title lang="th">ภาพยนตร์ 102 ปิดกรุงเทพปล้น</title>
    <desc lang="th">-</desc>
  </programme>
  <programme start="20251016022500 +0700" stop="20251016025500 +0700" channel="GMM25">
    <title lang="th">Music</title>
    <desc lang="th">-</desc>
  </programme>
  <programme start="20251016025500 +0700" stop="20251016031500 +0700" channel="GMM25">
    <title lang="th">O Shopping</title>
    <desc lang="th">-</desc>
  </programme>
  <programme start="20251016031500 +0700" stop="20251016033000 +0700" channel="GMM25">
    <title lang="th">Music</title>
    <desc lang="th">-</desc>
  </programme>
  <programme start="20251016033000 +0700" stop="20251016035000 +0700" channel="GMM25">
    <title lang="th">O Shopping</title>
    <desc lang="th">-</desc>
  </programme>
  <programme start="20251016035000 +0700" stop="20251016045000 +0700" channel="GMM25">
    <title lang="th">ธรรมนำชีวิต</title>
    <desc lang="th">-</desc>
  </programme>
  <programme start="20251016045000 +0700" stop="20251016051000 +0700" channel="GMM25">
    <title lang="th">O Shopping</title>
    <desc lang="th">-</desc>
  </programme>
  <programme start="20251016051000 +0700" stop="20251016054500 +0700" channel="GMM25">
    <title lang="th">Music</title>
    <desc lang="th">-</desc>
  </programme>
  <programme start="20251016054500 +0700" stop="20251016060000 +0700" channel="GMM25">
    <title lang="th">True Shopping</title>
    <desc lang="th">-</desc>
  </programme>
  <programme start="20251016060000 +0700" stop="20251016071000 +0700" channel="GMM25">
    <title lang="th">ไทยทึ่ง Wow Thailand (AD/CC/SL)</title>
    <desc lang="th">-</desc>
  </programme>
  <programme start="20251016071000 +0700" stop="20251016083000 +0700" channel="GMM25">
    <title lang="th">ข่าวแหกโค้ง (Rerun)</title>
    <desc lang="th">-</desc>
  </programme>
  <programme start="20251016083000 +0700" stop="20251016093000 +0700" channel="GMM25">
    <title lang="th">เรื่องใหญ่รายวัน</title>
    <desc lang="th">-</desc>
  </programme>
  <programme start="20251016093000 +0700" stop="20251016103000 +0700" channel="GMM25">
    <title lang="th">เคาะข่าวเช้า จันทร์-ศุกร์ (สด)</title>
    <desc lang="th">-</desc>
  </programme>
  <programme start="20251016103000 +0700" stop="20251016123000 +0700" channel="GMM25">
    <title lang="th">ละคร วิมานจอเงิน</title>
    <desc lang="th">-</desc>
  </programme>
  <programme start="20251016123000 +0700" stop="20251016133000 +0700" channel="GMM25">
    <title lang="th">ข่าวเที่ยงช่องวัน</title>
    <desc lang="th">-</desc>
  </programme>
  <programme start="20251016133000 +0700" stop="20251016150000 +0700" channel="GMM25">
    <title lang="th">แฉ</title>
    <desc lang="th">-</desc>
  </programme>
  <programme start="20251016150000 +0700" stop="20251016160000 +0700" channel="GMM25">
    <title lang="th">ไทยทึ่ง Wow Thailand (AD/CC/SL)</title>
    <desc lang="th">-</desc>
  </programme>
  <programme start="20251016160000 +0700" stop="20251016184500 +0700" channel="GMM25">
    <title lang="th">ละคร ดาวจรัสฟ้า</title>
    <desc lang="th">-</desc>
  </programme>
  <programme start="20251016184500 +0700" stop="20251016201500 +0700" channel="GMM25">
    <title lang="th">ข่าวแหกโค้ง (สด)</title>
    <desc lang="th">-</desc>
  </programme>
  <programme start="20251016201500 +0700" stop="20251016203000 +0700" channel="GMM25">
    <title lang="th">ข่าวในพระราชสำนัก</title>
    <desc lang="th">-</desc>
  </programme>
  <programme start="20251016203000 +0700" stop="20251016213000 +0700" channel="GMM25">
    <title lang="th">ซีรีส์ Sotus S The Series</title>
    <desc lang="th">-</desc>
  </programme>
  <programme start="20251016213000 +0700" stop="20251016230000 +0700" channel="GMM25">
    <title lang="th">แฉ (สด)</title>
    <desc lang="th">-</desc>
  </programme>
  <programme start="20251016230000 +0700" stop="20251016230500 +0700" channel="GMM25">
    <title lang="th">Music</title>
    <desc lang="th">-</desc>
  </programme>
  <programme start="20251016230500 +0700" stop="20251016235900 +0700" channel="GMM25">
    <title lang="th">เกลือวันเด้อ</title>
    <desc lang="th">-</desc>
  </programme>
  <programme start="20251016040000 +0700" stop="20251016042000 +0700" channel="TOPNew">
    <title lang="th">Rerun วัยรุ่น 90</title>
    <desc lang="th">-</desc>
  </programme>
  <programme start="20251016042000 +0700" stop="20251016060000 +0700" channel="TOPNew">
    <title lang="th">Rerun เล่าข่าวข้น</title>
    <desc lang="th">-</desc>
  </programme>
  <programme start="20251016060000 +0700" stop="20251016061000 +0700" channel="TOPNew">
    <title lang="th">TV Direct</title>
    <desc lang="th">-</desc>
  </programme>
  <programme start="20251016061000 +0700" stop="20251016080000 +0700" channel="TOPNew">
    <title lang="th">ข่าวมีคม</title>
    <desc lang="th">-</desc>
  </programme>
  <programme start="20251016080000 +0700" stop="20251016080200 +0700" channel="TOPNew">
    <title lang="th">เคารพธงชาติ</title>
    <desc lang="th">-</desc>
  </programme>
  <programme start="20251016080200 +0700" stop="20251016081000 +0700" channel="TOPNew">
    <title lang="th">ข่าวมีคม</title>
    <desc lang="th">-</desc>
  </programme>
  <programme start="20251016081000 +0700" stop="20251016082000 +0700" channel="TOPNew">
    <title lang="th">TV Direct</title>
    <desc lang="th">-</desc>
  </programme>
  <programme start="20251016082000 +0700" stop="20251016100000 +0700" channel="TOPNew">
    <title lang="th">เช้าข่าวเข้ม</title>
    <desc lang="th">-</desc>
  </programme>
  <programme start="20251016100000 +0700" stop="20251016101000 +0700" channel="TOPNew">
    <title lang="th">เรื่องดีมีสุข</title>
    <desc lang="th">-</desc>
  </programme>
  <programme start="20251016101000 +0700" stop="20251016105000 +0700" channel="TOPNew">
    <title lang="th">ผ่าประเด็นโลก</title>
    <desc lang="th">-</desc>
  </programme>
  <programme start="20251016105000 +0700" stop="20251016115000 +0700" channel="TOPNew">
    <title lang="th">จับตาประเทศไทย</title>
    <desc lang="th">-</desc>
  </programme>
  <programme start="20251016115000 +0700" stop="20251016120000 +0700" channel="TOPNew">
    <title lang="th">TV Direct</title>
    <desc lang="th">-</desc>
  </programme>
  <programme start="20251016120000 +0700" stop="20251016145000 +0700" channel="TOPNew">
    <title lang="th">เจาะข่าวเด่น (Top ทั่วไทย / ลึกจริงเศรษฐกิจ Top Biz Inside)</title>
    <desc lang="th">-</desc>
  </programme>
  <programme start="20251016145000 +0700" stop="20251016155000 +0700" channel="TOPNew">
    <title lang="th">Top Talk เรื่องนี้ต้องเคลียร์</title>
    <desc lang="th">-</desc>
  </programme>
  <programme start="20251016155000 +0700" stop="20251016160000 +0700" channel="TOPNew">
    <title lang="th">TV Direct</title>
    <desc lang="th">-</desc>
  </programme>
  <programme start="20251016160000 +0700" stop="20251016170000 +0700" channel="TOPNew">
    <title lang="th">Rerun ลายกนกยกสยาม</title>
    <desc lang="th">-</desc>
  </programme>
  <programme start="20251016170000 +0700" stop="20251016172000 +0700" channel="TOPNew">
    <title lang="th">TOP HEALTH STORY สุขภาพแบบท็อปๆ</title>
    <desc lang="th">-</desc>
  </programme>
  <programme start="20251016172000 +0700" stop="20251016180000 +0700" channel="TOPNew">
    <title lang="th">ข่าวเป็นข่าว</title>
    <desc lang="th">-</desc>
  </programme>
  <programme start="20251016180000 +0700" stop="20251016180200 +0700" channel="TOPNew">
    <title lang="th">เคารพธงชาติ</title>
    <desc lang="th">-</desc>
  </programme>
  <programme start="20251016180200 +0700" stop="20251016191500 +0700" channel="TOPNew">
    <title lang="th">ข่าวเป็นข่าว</title>
    <desc lang="th">-</desc>
  </programme>
  <programme start="20251016191500 +0700" stop="20251016192500 +0700" channel="TOPNew">
    <title lang="th">เรื่องดีมีสุข</title>
    <desc lang="th">-</desc>
  </programme>
  <programme start="20251016192500 +0700" stop="20251016200000 +0700" channel="TOPNew">
    <title lang="th">เล่าข่าวข้น</title>
    <desc lang="th">-</desc>
  </programme>
  <programme start="20251016200000 +0700" stop="20251016201500 +0700" channel="TOPNew">
    <title lang="th">ข่าวในพระราชสำนัก</title>
    <desc lang="th">-</desc>
  </programme>
  <programme start="20251016201500 +0700" stop="20251016212000 +0700" channel="TOPNew">
    <title lang="th">เล่าข่าวข้น</title>
    <desc lang="th">-</desc>
  </programme>
  <programme start="20251016212000 +0700" stop="20251016213000 +0700" channel="TOPNew">
    <title lang="th">เรื่องดีมีสุข</title>
    <desc lang="th">-</desc>
  </programme>
  <programme start="20251016213000 +0700" stop="20251016215000 +0700" channel="TOPNew">
    <title lang="th">เจาะประเด็นโลก</title>
    <desc lang="th">-</desc>
  </programme>
  <programme start="20251016215000 +0700" stop="20251016221000 +0700" channel="TOPNew">
    <title lang="th">Rerun TOP HEALTH STORY สุขภาพแบบท็อปๆ</title>
    <desc lang="th">-</desc>
  </programme>
  <programme start="20251016221000 +0700" stop="20251016235900 +0700" channel="TOPNew">
    <title lang="th">Rerun ข่าวเป็นข่าว</title>
    <desc lang="th">-</desc>
  </programme>
  <programme start="20251016050000 +0700" stop="20251016070000 +0700" channel="TPBS">
    <title lang="th">วันใหม่ ไทยพีบีเอส</title>
    <desc lang="th">-</desc>
  </programme>
  <programme start="20251016070000 +0700" stop="20251016080000 +0700" channel="TPBS">
    <title lang="th">มุมการเมือง</title>
    <desc lang="th">-</desc>
  </programme>
  <programme start="20251016080000 +0700" stop="20251016100000 +0700" channel="TPBS">
    <title lang="th">วันใหม่วาไรตี้</title>
    <desc lang="th">-</desc>
  </programme>
  <programme start="20251016100000 +0700" stop="20251016103000 +0700" channel="TPBS">
    <title lang="th">ไทยบันเทิง</title>
    <desc lang="th">-</desc>
  </programme>
  <programme start="20251016103000 +0700" stop="20251016120000 +0700" channel="TPBS">
    <title lang="th">จับตาสถานการณ์</title>
    <desc lang="th">-</desc>
  </programme>
  <programme start="20251016120000 +0700" stop="20251016123000 +0700" channel="TPBS">
    <title lang="th">ตรงประเด็น</title>
    <desc lang="th">-</desc>
  </programme>
  <programme start="20251016123000 +0700" stop="20251016130000 +0700" channel="TPBS">
    <title lang="th">จับตารอบทิศ</title>
    <desc lang="th">-</desc>
  </programme>
  <programme start="20251016130000 +0700" stop="20251016140000 +0700" channel="TPBS">
    <title lang="th">8 ยอดมนุษย์ธรรมดา</title>
    <desc lang="th">-</desc>
  </programme>
  <programme start="20251016140000 +0700" stop="20251016140500 +0700" channel="TPBS">
    <title lang="th">ทันข่าว 14.00 น.</title>
    <desc lang="th">-</desc>
  </programme>
  <programme start="20251016140500 +0700" stop="20251016150000 +0700" channel="TPBS">
    <title lang="th">สถานีประชาชน</title>
    <desc lang="th">-</desc>
  </programme>
  <programme start="20251016150000 +0700" stop="20251016150500 +0700" channel="TPBS">
    <title lang="th">ทันข่าว 15.00 น.</title>
    <desc lang="th">-</desc>
  </programme>
  <programme start="20251016150500 +0700" stop="20251016153000 +0700" channel="TPBS">
    <title lang="th">ลุยไม่รู้โรย</title>
    <desc lang="th">-</desc>
  </programme>
  <programme start="20251016153000 +0700" stop="20251016160000 +0700" channel="TPBS">
    <title lang="th">ทุกทิศทั่วไทย</title>
    <desc lang="th">-</desc>
  </programme>
  <programme start="20251016160000 +0700" stop="20251016163000 +0700" channel="TPBS">
    <title lang="th">ข่าว 16.00 น.</title>
    <desc lang="th">-</desc>
  </programme>
  <programme start="20251016163000 +0700" stop="20251016164500 +0700" channel="TPBS">
    <title lang="th">เสียงเปลี่ยนเมือง</title>
    <desc lang="th">-</desc>
  </programme>
  <programme start="20251016164500 +0700" stop="20251016170000 +0700" channel="TPBS">
    <title lang="th">ไทยบันเทิง</title>
    <desc lang="th">-</desc>
  </programme>
  <programme start="20251016170000 +0700" stop="20251016180000 +0700" channel="TPBS">
    <title lang="th">ท่องโลกกว้าง</title>
    <desc lang="th">-</desc>
  </programme>
  <programme start="20251016180000 +0700" stop="20251016203000 +0700" channel="TPBS">
    <title lang="th">ข่าวค่ำ</title>
    <desc lang="th">-</desc>
  </programme>
  <programme start="20251016203000 +0700" stop="20251016210000 +0700" channel="TPBS">
    <title lang="th">ตอบโจทย์</title>
    <desc lang="th">-</desc>
  </programme>
  <programme start="20251016210000 +0700" stop="20251016213000 +0700" channel="TPBS">
    <title lang="th">ทันโลก กับ Thai PBS</title>
    <desc lang="th">-</desc>
  </programme>
  <programme start="20251016213000 +0700" stop="20251016220000 +0700" channel="TPBS">
    <title lang="th">คุยนอกกรอบ กับ สุทธิชัย หยุ่น</title>
    <desc lang="th">-</desc>
  </programme>
  <programme start="20251016220000 +0700" stop="20251016230000 +0700" channel="TPBS">
    <title lang="th">Big Story เรื่องใหญ่ Thai PBS</title>
    <desc lang="th">-</desc>
  </programme>
  <programme start="20251016230000 +0700" stop="20251016233000 +0700" channel="TPBS">
    <title lang="th">ข่าวดึก</title>
    <desc lang="th">-</desc>
  </programme>
  <programme start="20251016233000 +0700" stop="20251016235900 +0700" channel="TPBS">
    <title lang="th">ทุกทิศทั่วไทย</title>
    <desc lang="th">-</desc>
  </programme>
  <programme start="20251016025000 +0700" stop="20251016035000 +0700" channel="8SD">
    <title lang="th">อึ้งทึ่งเสียว</title>
    <desc lang="th">-</desc>
  </programme>
  <programme start="20251016035000 +0700" stop="20251016042000 +0700" channel="8SD">
    <title lang="th">เรื่องว้าวเล่าโลก</title>
    <desc lang="th">-</desc>
  </programme>
  <programme start="20251016042000 +0700" stop="20251016043000 +0700" channel="8SD">
    <title lang="th">ชีวิตดี สาระดี</title>
    <desc lang="th">-</desc>
  </programme>
  <programme start="20251016043000 +0700" stop="20251016050000 +0700" channel="8SD">
    <title lang="th">ลุยชนข่าว</title>
    <desc lang="th">-</desc>
  </programme>
  <programme start="20251016050000 +0700" stop="20251016053000 +0700" channel="8SD">
    <title lang="th">ลุยชนข่าว</title>
    <desc lang="th">-</desc>
  </programme>
  <programme start="20251016053000 +0700" stop="20251016080000 +0700" channel="8SD">
    <title lang="th">คุยข่าวเช้าช่อง 8</title>
    <desc lang="th">-</desc>
  </programme>
  <programme start="20251016080000 +0700" stop="20251016085000 +0700" channel="8SD">
    <title lang="th">เช้านี้ขยี้ข่าว</title>
    <desc lang="th">-</desc>
  </programme>
  <programme start="20251016085000 +0700" stop="20251016101000 +0700" channel="8SD">
    <title lang="th">ซีรีส์อินเดีย กรงรักกับดักหัวใจ</title>
    <desc lang="th">-</desc>
  </programme>
  <programme start="20251016101000 +0700" stop="20251016102000 +0700" channel="8SD">
    <title lang="th">ชีวิตดี สาระดี</title>
    <desc lang="th">-</desc>
  </programme>
  <programme start="20251016102000 +0700" stop="20251016105000 +0700" channel="8SD">
    <title lang="th">ลุยข่าวเกษตร</title>
    <desc lang="th">-</desc>
  </programme>
  <programme start="20251016105000 +0700" stop="20251016124500 +0700" channel="8SD">
    <title lang="th">ข่าวใหญ่ช่อง 8</title>
    <desc lang="th">-</desc>
  </programme>
  <programme start="20251016124500 +0700" stop="20251016125500 +0700" channel="8SD">
    <title lang="th">ชีวิตดี สาระดี</title>
    <desc lang="th">-</desc>
  </programme>
  <programme start="20251016125500 +0700" stop="20251016140500 +0700" channel="8SD">
    <title lang="th">ซีรีส์ ดรุณพเนจรท่องยุทธภพ</title>
    <desc lang="th">-</desc>
  </programme>
  <programme start="20251016140500 +0700" stop="20251016150500 +0700" channel="8SD">
    <title lang="th">คนดังนั่งเคลียร์</title>
    <desc lang="th">-</desc>
  </programme>
  <programme start="20251016150500 +0700" stop="20251016163000 +0700" channel="8SD">
    <title lang="th">ซีรีส์อินเดีย มหากาพย์นารายณ์ลักษมี</title>
    <desc lang="th">-</desc>
  </programme>
  <programme start="20251016163000 +0700" stop="20251016164000 +0700" channel="8SD">
    <title lang="th">ชีวิตดี สาระดี</title>
    <desc lang="th">-</desc>
  </programme>
  <programme start="20251016164000 +0700" stop="20251016180000 +0700" channel="8SD">
    <title lang="th">ละคร บ่วงใบบุญ</title>
    <desc lang="th">-</desc>
  </programme>
  <programme start="20251016180000 +0700" stop="20251016190000 +0700" channel="8SD">
    <title lang="th">ละคร ผีตาโขน</title>
    <desc lang="th">-</desc>
  </programme>
  <programme start="20251016190000 +0700" stop="20251016200000 +0700" channel="8SD">
    <title lang="th">ลุยชนข่าว</title>
    <desc lang="th">-</desc>
  </programme>
  <programme start="20251016200000 +0700" stop="20251016202000 +0700" channel="8SD">
    <title lang="th">ข่าวในพระราชสำนัก</title>
    <desc lang="th">-</desc>
  </programme>
  <programme start="20251016202000 +0700" stop="20251016220000 +0700" channel="8SD">
    <title lang="th">ลุยชนข่าว</title>
    <desc lang="th">-</desc>
  </programme>
  <programme start="20251016220000 +0700" stop="20251016221500 +0700" channel="8SD">
    <title lang="th">ลุยชนข่าว The X-Files</title>
    <desc lang="th">-</desc>
  </programme>
  <programme start="20251016221500 +0700" stop="20251016231500 +0700" channel="8SD">
    <title lang="th">ซีรีส์เกาหลี รักแค้นข้ามภพ</title>
    <desc lang="th">-</desc>
  </programme>
  <programme start="20251016231500 +0700" stop="20251016235900 +0700" channel="8SD">
    <title lang="th">ซีรีส์ ดรุณพเนจรท่องยุทธภพ</title>
    <desc lang="th">-</desc>
  </programme>
  <programme start="20251016030000 +0700" stop="20251016040000 +0700" channel="Boomerang">
    <title lang="th">Hello Jadoo</title>
    <desc lang="th">-</desc>
  </programme>
  <programme start="20251016040000 +0700" stop="20251016050000 +0700" channel="Boomerang">
    <title lang="th">Dragons Guardian</title>
    <desc lang="th">-</desc>
  </programme>
  <programme start="20251016050000 +0700" stop="20251016053000 +0700" channel="Boomerang">
    <title lang="th">Super Wings 3</title>
    <desc lang="th">-</desc>
  </programme>
  <programme start="20251016053000 +0700" stop="20251016060000 +0700" channel="Boomerang">
    <title lang="th">Gogobus S2+Katuri</title>
    <desc lang="th">-</desc>
  </programme>
  <programme start="20251016060000 +0700" stop="20251016063000 +0700" channel="Boomerang">
    <title lang="th">Tobot 6 + Dinoman 33</title>
    <desc lang="th">-</desc>
  </programme>
  <programme start="20251016063000 +0700" stop="20251016070000 +0700" channel="Boomerang">
    <title lang="th">Smurfs</title>
    <desc lang="th">-</desc>
  </programme>
  <programme start="20251016070000 +0700" stop="20251016073000 +0700" channel="Boomerang">
    <title lang="th">The Garfield Show</title>
    <desc lang="th">-</desc>
  </programme>
  <programme start="20251016073000 +0700" stop="20251016080000 +0700" channel="Boomerang">
    <title lang="th">Boonie Cubs</title>
    <desc lang="th">-</desc>
  </programme>
  <programme start="20251016080000 +0700" stop="20251016083000 +0700" channel="Boomerang">
    <title lang="th">Astro boy go 29+Zombie Dumb 49-52</title>
    <desc lang="th">-</desc>
  </programme>
  <programme start="20251016083000 +0700" stop="20251016090000 +0700" channel="Boomerang">
    <title lang="th">Wheewheel</title>
    <desc lang="th">-</desc>
  </programme>
  <programme start="20251016090000 +0700" stop="20251016093000 +0700" channel="Boomerang">
    <title lang="th">Super Wings 2</title>
    <desc lang="th">-</desc>
  </programme>
  <programme start="20251016093000 +0700" stop="20251016100000 +0700" channel="Boomerang">
    <title lang="th">Hello Jadoo</title>
    <desc lang="th">-</desc>
  </programme>
  <programme start="20251016100000 +0700" stop="20251016103000 +0700" channel="Boomerang">
    <title lang="th">Smurfs</title>
    <desc lang="th">-</desc>
  </programme>
  <programme start="20251016103000 +0700" stop="20251016110000 +0700" channel="Boomerang">
    <title lang="th">Johnny Test</title>
    <desc lang="th">-</desc>
  </programme>
  <programme start="20251016110000 +0700" stop="20251016113000 +0700" channel="Boomerang">
    <title lang="th">Adventure Of Kaka The Tiger</title>
    <desc lang="th">-</desc>
  </programme>
  <programme start="20251016113000 +0700" stop="20251016120000 +0700" channel="Boomerang">
    <title lang="th">Garfield Show</title>
    <desc lang="th">-</desc>
  </programme>
  <programme start="20251016120000 +0700" stop="20251016123000 +0700" channel="Boomerang">
    <title lang="th">Super Wings 2</title>
    <desc lang="th">-</desc>
  </programme>
  <programme start="20251016123000 +0700" stop="20251016130000 +0700" channel="Boomerang">
    <title lang="th">Boonie Cubs</title>
    <desc lang="th">-</desc>
  </programme>
  <programme start="20251016130000 +0700" stop="20251016133000 +0700" channel="Boomerang">
    <title lang="th">Future Card BuddyFight (ปี1) 12</title>
    <desc lang="th">-</desc>
  </programme>
  <programme start="20251016133000 +0700" stop="20251016140000 +0700" channel="Boomerang">
    <title lang="th">BeyBlade X (ปี1) 27</title>
    <desc lang="th">-</desc>
  </programme>
  <programme start="20251016140000 +0700" stop="20251016143000 +0700" channel="Boomerang">
    <title lang="th">Super Wings 2</title>
    <desc lang="th">-</desc>
  </programme>
  <programme start="20251016143000 +0700" stop="20251016150000 +0700" channel="Boomerang">
    <title lang="th">Smurfs</title>
    <desc lang="th">-</desc>
  </programme>
  <programme start="20251016150000 +0700" stop="20251016153000 +0700" channel="Boomerang">
    <title lang="th">Tobot 6 + Dinoman 33</title>
    <desc lang="th">-</desc>
  </programme>
  <programme start="20251016153000 +0700" stop="20251016160000 +0700" channel="Boomerang">
    <title lang="th">GG Bond : Dodgeball Legend</title>
    <desc lang="th">-</desc>
  </programme>
  <programme start="20251016160000 +0700" stop="20251016163000 +0700" channel="Boomerang">
    <title lang="th">Astro boy go 29+Zombie Dumb 49-52</title>
    <desc lang="th">-</desc>
  </programme>
  <programme start="20251016163000 +0700" stop="20251016170000 +0700" channel="Boomerang">
    <title lang="th">Johnny Test</title>
    <desc lang="th">-</desc>
  </programme>
  <programme start="20251016170000 +0700" stop="20251016173000 +0700" channel="Boomerang">
    <title lang="th">Smurfs</title>
    <desc lang="th">-</desc>
  </programme>
  <programme start="20251016173000 +0700" stop="20251016180000 +0700" channel="Boomerang">
    <title lang="th">Strawberry Shortcake</title>
    <desc lang="th">-</desc>
  </programme>
  <programme start="20251016180000 +0700" stop="20251016183000 +0700" channel="Boomerang">
    <title lang="th">Super Wings 3</title>
    <desc lang="th">-</desc>
  </programme>
  <programme start="20251016183000 +0700" stop="20251016190000 +0700" channel="Boomerang">
    <title lang="th">Hello Jadoo</title>
    <desc lang="th">-</desc>
  </programme>
  <programme start="20251016190000 +0700" stop="20251016193000 +0700" channel="Boomerang">
    <title lang="th">Wheewheel</title>
    <desc lang="th">-</desc>
  </programme>
  <programme start="20251016193000 +0700" stop="20251016200000 +0700" channel="Boomerang">
    <title lang="th">Boonie Cubs</title>
    <desc lang="th">-</desc>
  </programme>
  <programme start="20251016200000 +0700" stop="20251016203000 +0700" channel="Boomerang">
    <title lang="th">My Little Pony: Friendship Is Magic S1</title>
    <desc lang="th">-</desc>
  </programme>
  <programme start="20251016203000 +0700" stop="20251016210000 +0700" channel="Boomerang">
    <title lang="th">Wheewheel</title>
    <desc lang="th">-</desc>
  </programme>
  <programme start="20251016210000 +0700" stop="20251016213000 +0700" channel="Boomerang">
    <title lang="th">Card Fight vanguard G (ปี5) 12</title>
    <desc lang="th">-</desc>
  </programme>
  <programme start="20251016213000 +0700" stop="20251016220000 +0700" channel="Boomerang">
    <title lang="th">Kiramager 2</title>
    <desc lang="th">-</desc>
  </programme>
  <programme start="20251016220000 +0700" stop="20251016223000 +0700" channel="Boomerang">
    <title lang="th">Pokemon (ปี23) 4</title>
    <desc lang="th">-</desc>
  </programme>
  <programme start="20251016223000 +0700" stop="20251016230000 +0700" channel="Boomerang">
    <title lang="th">Ninja Hattori Returns 55</title>
    <desc lang="th">-</desc>
  </programme>
  <programme start="20251016230000 +0700" stop="20251016233000 +0700" channel="Boomerang">
    <title lang="th">Ryusoulger 4</title>
    <desc lang="th">-</desc>
  </programme>
  <programme start="20251016233000 +0700" stop="20251016235900 +0700" channel="Boomerang">
    <title lang="th">Future Card BuddyFight (ปี1) 6</title>
    <desc lang="th">-</desc>
  </programme>
  <programme start="20251016030000 +0700" stop="20251016043000 +0700" channel="TNN">
    <title lang="th">TNN ข่าวดึก</title>
    <desc lang="th">-</desc>
  </programme>
  <programme start="20251016043000 +0700" stop="20251016053000 +0700" channel="TNN">
    <title lang="th">I Need Romance รักใช่ไหมที่หัวใจต้องการ</title>
    <desc lang="th">-</desc>
  </programme>
  <programme start="20251016053000 +0700" stop="20251016060000 +0700" channel="TNN">
    <title lang="th">TNN สตาร์ตอัป</title>
    <desc lang="th">-</desc>
  </programme>
  <programme start="20251016060000 +0700" stop="20251016080000 +0700" channel="TNN">
    <title lang="th">TNN ข่าวเช้า</title>
    <desc lang="th">-</desc>
  </programme>
  <programme start="20251016080000 +0700" stop="20251016083000 +0700" channel="TNN">
    <title lang="th">เศรษฐกิจอินไซต์</title>
    <desc lang="th">-</desc>
  </programme>
  <programme start="20251016083000 +0700" stop="20251016090000 +0700" channel="TNN">
    <title lang="th">TNN ข่าวเช้า</title>
    <desc lang="th">-</desc>
  </programme>
  <programme start="20251016090000 +0700" stop="20251016093000 +0700" channel="TNN">
    <title lang="th">เรื่องดีดีทั่วไทย</title>
    <desc lang="th">-</desc>
  </programme>
  <programme start="20251016093000 +0700" stop="20251016103000 +0700" channel="TNN">
    <title lang="th">ชั่วโมงทำเงิน</title>
    <desc lang="th">-</desc>
  </programme>
  <programme start="20251016103000 +0700" stop="20251016110000 +0700" channel="TNN">
    <title lang="th">TNN สปอร์ต</title>
    <desc lang="th">-</desc>
  </programme>
  <programme start="20251016110000 +0700" stop="20251016113000 +0700" channel="TNN">
    <title lang="th">การตลาดเงินล้าน</title>
    <desc lang="th">-</desc>
  </programme>
  <programme start="20251016113000 +0700" stop="20251016133000 +0700" channel="TNN">
    <title lang="th">TNN ข่าวเที่ยง</title>
    <desc lang="th">-</desc>
  </programme>
  <programme start="20251016133000 +0700" stop="20251016133200 +0700" channel="TNN">
    <title lang="th">TNN บิซนิวส์</title>
    <desc lang="th">-</desc>
  </programme>
  <programme start="20251016133200 +0700" stop="20251016140000 +0700" channel="TNN">
    <title lang="th">คนชนข่าว</title>
    <desc lang="th">-</desc>
  </programme>
  <programme start="20251016140000 +0700" stop="20251016140500 +0700" channel="TNN">
    <title lang="th">TNN ข่าวต้นชั่วโมง</title>
    <desc lang="th">-</desc>
  </programme>
  <programme start="20251016140500 +0700" stop="20251016143000 +0700" channel="TNN">
    <title lang="th">เศรษฐกิจอินไซต์</title>
    <desc lang="th">-</desc>
  </programme>
  <programme start="20251016143000 +0700" stop="20251016150000 +0700" channel="TNN">
    <title lang="th">ย่อโลกเศรษฐกิจ</title>
    <desc lang="th">-</desc>
  </programme>
  <programme start="20251016150000 +0700" stop="20251016153000 +0700" channel="TNN">
    <title lang="th">คนหลังข่าว</title>
    <desc lang="th">-</desc>
  </programme>
  <programme start="20251016153000 +0700" stop="20251016160000 +0700" channel="TNN">
    <title lang="th">เรื่องดีดีทั่วไทย</title>
    <desc lang="th">-</desc>
  </programme>
  <programme start="20251016160000 +0700" stop="20251016165000 +0700" channel="TNN">
    <title lang="th">บิสเนสวอตช์</title>
    <desc lang="th">-</desc>
  </programme>
  <programme start="20251016165000 +0700" stop="20251016170000 +0700" channel="TNN">
    <title lang="th">TNN เทครีพอตส์</title>
    <desc lang="th">-</desc>
  </programme>
  <programme start="20251016170000 +0700" stop="20251016180000 +0700" channel="TNN">
    <title lang="th">TNN รู้ทันลงทุน</title>
    <desc lang="th">-</desc>
  </programme>
  <programme start="20251016180000 +0700" stop="20251016195700 +0700" channel="TNN">
    <title lang="th">TNN ข่าวค่ำ</title>
    <desc lang="th">-</desc>
  </programme>
  <programme start="20251016195700 +0700" stop="20251016200500 +0700" channel="TNN">
    <title lang="th">TNN เทครีพอตส์</title>
    <desc lang="th">-</desc>
  </programme>
  <programme start="20251016200500 +0700" stop="20251016203000 +0700" channel="TNN">
    <title lang="th">ข่าวในพระราชสำนัก</title>
    <desc lang="th">-</desc>
  </programme>
  <programme start="20251016203000 +0700" stop="20251016211500 +0700" channel="TNN">
    <title lang="th">TNN เวิลด์ ทูเดย์</title>
    <desc lang="th">-</desc>
  </programme>
  <programme start="20251016211500 +0700" stop="20251016211700 +0700" channel="TNN">
    <title lang="th">TNN บิซนิวส์</title>
    <desc lang="th">-</desc>
  </programme>
  <programme start="20251016211700 +0700" stop="20251016220000 +0700" channel="TNN">
    <title lang="th">บิสเนสวอตช์</title>
    <desc lang="th">-</desc>
  </programme>
  <programme start="20251016220000 +0700" stop="20251016223000 +0700" channel="TNN">
    <title lang="th">มันนี่ทูเดย์</title>
    <desc lang="th">-</desc>
  </programme>
  <programme start="20251016223000 +0700" stop="20251016235900 +0700" channel="TNN">
    <title lang="th">TNN ข่าวดึก</title>
    <desc lang="th">-</desc>
  </programme>
  <programme start="20251016040000 +0700" stop="20251016043000 +0700" channel="5HD">
    <title lang="th">ทรู ช้อปปิ้ง</title>
    <desc lang="th">-</desc>
  </programme>
  <programme start="20251016043000 +0700" stop="20251016050000 +0700" channel="5HD">
    <title lang="th">แนะนำสินค้า</title>
    <desc lang="th">-</desc>
  </programme>
  <programme start="20251016050000 +0700" stop="20251016053000 +0700" channel="5HD">
    <title lang="th">สายธารแสงธรรม</title>
    <desc lang="th">-</desc>
  </programme>
  <programme start="20251016053000 +0700" stop="20251016060000 +0700" channel="5HD">
    <title lang="th">อรุณสวัสดิ์ยามเช้า (Re)</title>
    <desc lang="th">-</desc>
  </programme>
  <programme start="20251016060000 +0700" stop="20251016063000 +0700" channel="5HD">
    <title lang="th">เคาะข่าวเด่น</title>
    <desc lang="th">-</desc>
  </programme>
  <programme start="20251016063000 +0700" stop="20251016070000 +0700" channel="5HD">
    <title lang="th">ต้นกล้าพหุวัฒนธรรม (Re)</title>
    <desc lang="th">-</desc>
  </programme>
  <programme start="20251016070000 +0700" stop="20251016080000 +0700" channel="5HD">
    <title lang="th">ข่าวเด่นเช้านี้ (สด)</title>
    <desc lang="th">-</desc>
  </programme>
  <programme start="20251016080000 +0700" stop="20251016085500 +0700" channel="5HD">
    <title lang="th">สนทนาปัญหาประชาชน Talk Together</title>
    <desc lang="th">-</desc>
  </programme>
  <programme start="20251016085500 +0700" stop="20251016090000 +0700" channel="5HD">
    <title lang="th">สารคดี</title>
    <desc lang="th">-</desc>
  </programme>
  <programme start="20251016090000 +0700" stop="20251016090500 +0700" channel="5HD">
    <title lang="th">เบรคกิ้งนิวส์ (สด)</title>
    <desc lang="th">-</desc>
  </programme>
  <programme start="20251016090500 +0700" stop="20251016093000 +0700" channel="5HD">
    <title lang="th">ไขรหัสแดนมหัศจรรย์</title>
    <desc lang="th">-</desc>
  </programme>
  <programme start="20251016093000 +0700" stop="20251016100000 +0700" channel="5HD">
    <title lang="th">เกษตรไดเร็ค</title>
    <desc lang="th">-</desc>
  </programme>
  <programme start="20251016100000 +0700" stop="20251016100500 +0700" channel="5HD">
    <title lang="th">เบรคกิ้งนิวส์ (สด)</title>
    <desc lang="th">-</desc>
  </programme>
  <programme start="20251016100500 +0700" stop="20251016102000 +0700" channel="5HD">
    <title lang="th">พ่อมดรถยนต์</title>
    <desc lang="th">-</desc>
  </programme>
  <programme start="20251016102000 +0700" stop="20251016104500 +0700" channel="5HD">
    <title lang="th">โลกไร้กรอบ  (Worldwide Code)</title>
    <desc lang="th">-</desc>
  </programme>
  <programme start="20251016104500 +0700" stop="20251016111500 +0700" channel="5HD">
    <title lang="th">ทรู ช้อปปิ้ง</title>
    <desc lang="th">-</desc>
  </programme>
  <programme start="20251016111500 +0700" stop="20251016114500 +0700" channel="5HD">
    <title lang="th">ถอดรหัสธรรมชาติ (Nature Code)</title>
    <desc lang="th">-</desc>
  </programme>
  <programme start="20251016114500 +0700" stop="20251016120000 +0700" channel="5HD">
    <title lang="th">ทางออกเกษตรกรไทย</title>
    <desc lang="th">-</desc>
  </programme>
  <programme start="20251016120000 +0700" stop="20251016130000 +0700" channel="5HD">
    <title lang="th">เที่ยงวันทันข่าว (สด)</title>
    <desc lang="th">-</desc>
  </programme>
  <programme start="20251016130000 +0700" stop="20251016133000 +0700" channel="5HD">
    <title lang="th">ตลาดสนามเป้า</title>
    <desc lang="th">-</desc>
  </programme>
  <programme start="20251016133000 +0700" stop="20251016135500 +0700" channel="5HD">
    <title lang="th">ทรู ช้อปปิ้ง</title>
    <desc lang="th">-</desc>
  </programme>
  <programme start="20251016135500 +0700" stop="20251016140000 +0700" channel="5HD">
    <title lang="th">ข่าวดี๊ดีกับพี่คำรณ</title>
    <desc lang="th">-</desc>
  </programme>
  <programme start="20251016140000 +0700" stop="20251016140500 +0700" channel="5HD">
    <title lang="th">เบรคกิ้งนิวส์ (สด)</title>
    <desc lang="th">-</desc>
  </programme>
  <programme start="20251016140500 +0700" stop="20251016143000 +0700" channel="5HD">
    <title lang="th">รู้รอบโลก (Knowledge Code)</title>
    <desc lang="th">-</desc>
  </programme>
  <programme start="20251016143000 +0700" stop="20251016150000 +0700" channel="5HD">
    <title lang="th">สุขแบบไทยใจพอเพียง</title>
    <desc lang="th">-</desc>
  </programme>
  <programme start="20251016150000 +0700" stop="20251016150500 +0700" channel="5HD">
    <title lang="th">เบรคกิ้งนิวส์ (สด)</title>
    <desc lang="th">-</desc>
  </programme>
  <programme start="20251016150500 +0700" stop="20251016153500 +0700" channel="5HD">
    <title lang="th">ร้อยเรื่องราว วาไรตี้</title>
    <desc lang="th">-</desc>
  </programme>
  <programme start="20251016153500 +0700" stop="20251016160000 +0700" channel="5HD">
    <title lang="th">มีเดีย ช้อปปิ้ง</title>
    <desc lang="th">-</desc>
  </programme>
  <programme start="20251016160000 +0700" stop="20251016160500 +0700" channel="5HD">
    <title lang="th">เบรคกิ้งนิวส์ (สด)</title>
    <desc lang="th">-</desc>
  </programme>
  <programme start="20251016160500 +0700" stop="20251016165000 +0700" channel="5HD">
    <title lang="th">ซีรีย์ ฮิตติดจอ</title>
    <desc lang="th">-</desc>
  </programme>
  <programme start="20251016165000 +0700" stop="20251016170000 +0700" channel="5HD">
    <title lang="th">สารคดี</title>
    <desc lang="th">-</desc>
  </programme>
  <programme start="20251016170000 +0700" stop="20251016180000 +0700" channel="5HD">
    <title lang="th">แฉมิจฉาชีพ</title>
    <desc lang="th">-</desc>
  </programme>
  <programme start="20251016180000 +0700" stop="20251016193000 +0700" channel="5HD">
    <title lang="th">ข่าวเด่นทันสถานการณ์ (สด)</title>
    <desc lang="th">-</desc>
  </programme>
  <programme start="20251016193000 +0700" stop="20251016200000 +0700" channel="5HD">
    <title lang="th">แทนคุณแผ่นดิน</title>
    <desc lang="th">-</desc>
  </programme>
  <programme start="20251016200000 +0700" stop="20251016203000 +0700" channel="5HD">
    <title lang="th">ข่าวในพระราชสำนัก</title>
    <desc lang="th">-</desc>
  </programme>
  <programme start="20251016203000 +0700" stop="20251016210000 +0700" channel="5HD">
    <title lang="th">กอ.รมน.เพื่อประชาชน(Re)</title>
    <desc lang="th">-</desc>
  </programme>
  <programme start="20251016210000 +0700" stop="20251016223000 +0700" channel="5HD">
    <title lang="th">ป่าตอง ไฟท์ ไนท์ (สด)</title>
    <desc lang="th">-</desc>
  </programme>
  <programme start="20251016223000 +0700" stop="20251016224500 +0700" channel="5HD">
    <title lang="th">มอเตอร์ รันนิ่ง</title>
    <desc lang="th">-</desc>
  </programme>
  <programme start="20251016224500 +0700" stop="20251016230000 +0700" channel="5HD">
    <title lang="th">แอทไทม์ (Re)</title>
    <desc lang="th">-</desc>
  </programme>
  <programme start="20251016230000 +0700" stop="20251016235900 +0700" channel="5HD">
    <title lang="th">เดินหน้าปฎิรูป /ปิดทองหลังพระ</title>
    <desc lang="th">-</desc>
  </programme>
  <programme start="20251016030000 +0700" stop="20251016040000 +0700" channel="JKN18">
    <title lang="th">รายการ หน้าต่างโลก</title>
    <desc lang="th">-</desc>
  </programme>
  <programme start="20251016040000 +0700" stop="20251016050000 +0700" channel="JKN18">
    <title lang="th">รายการ อัศจรรย์บันลือโลก</title>
    <desc lang="th">-</desc>
  </programme>
  <programme start="20251016050000 +0700" stop="20251016060000 +0700" channel="JKN18">
    <title lang="th">รายการ อัศจรรย์บันลือโลก</title>
    <desc lang="th">-</desc>
  </programme>
  <programme start="20251016060000 +0700" stop="20251016073000 +0700" channel="JKN18">
    <title lang="th">รายการ Hello Anniverse บันเทิง (Rerun)</title>
    <desc lang="th">-</desc>
  </programme>
  <programme start="20251016073000 +0700" stop="20251016080000 +0700" channel="JKN18">
    <title lang="th">รายการ Hello Anniverse เล่าข่าว (Rerun)</title>
    <desc lang="th">-</desc>
  </programme>
  <programme start="20251016080000 +0700" stop="20251016080200 +0700" channel="JKN18">
    <title lang="th">เพลงชาติไทย</title>
    <desc lang="th">-</desc>
  </programme>
  <programme start="20251016080200 +0700" stop="20251016085000 +0700" channel="JKN18">
    <title lang="th">ซีรีส์อินเดีย กฤษณะ อภินิหารมหาเทพอวตาร</title>
    <desc lang="th">-</desc>
  </programme>
  <programme start="20251016085000 +0700" stop="20251016091500 +0700" channel="JKN18">
    <title lang="th">รายการ Anniverse Shop</title>
    <desc lang="th">-</desc>
  </programme>
  <programme start="20251016091500 +0700" stop="20251016100000 +0700" channel="JKN18">
    <title lang="th">ซีรีส์อินเดีย โยดาห์ อัคบาร์ ศึกจารีตพิศ</title>
    <desc lang="th">-</desc>
  </programme>
  <programme start="20251016100000 +0700" stop="20251016101000 +0700" channel="JKN18">
    <title lang="th">รายการ Anniverse Shop</title>
    <desc lang="th">-</desc>
  </programme>
  <programme start="20251016101000 +0700" stop="20251016105500 +0700" channel="JKN18">
    <title lang="th">ซีรีส์อินเดีย กรงรักกับดักหัวใจ</title>
    <desc lang="th">-</desc>
  </programme>
  <programme start="20251016105500 +0700" stop="20251016112000 +0700" channel="JKN18">
    <title lang="th">รายการ Anniverse Shop</title>
    <desc lang="th">-</desc>
  </programme>
  <programme start="20251016112000 +0700" stop="20251016120500 +0700" channel="JKN18">
    <title lang="th">ซีรีส์อินเดีย เพียงเธอเท่านั้น</title>
    <desc lang="th">-</desc>
  </programme>
  <programme start="20251016120500 +0700" stop="20251016121500 +0700" channel="JKN18">
    <title lang="th">รายการ Anniverse Shop</title>
    <desc lang="th">-</desc>
  </programme>
  <programme start="20251016121500 +0700" stop="20251016130000 +0700" channel="JKN18">
    <title lang="th">ซีรีส์อินเดีย เพลิงรักสามหัวใจ</title>
    <desc lang="th">-</desc>
  </programme>
  <programme start="20251016130000 +0700" stop="20251016131000 +0700" channel="JKN18">
    <title lang="th">รายการ Anniverse Shop</title>
    <desc lang="th">-</desc>
  </programme>
  <programme start="20251016131000 +0700" stop="20251016140000 +0700" channel="JKN18">
    <title lang="th">ซีรีส์อินเดีย ลมเปลี่ยนรัก</title>
    <desc lang="th">-</desc>
  </programme>
  <programme start="20251016140000 +0700" stop="20251016142500 +0700" channel="JKN18">
    <title lang="th">รายการ Anniverse Shop</title>
    <desc lang="th">-</desc>
  </programme>
  <programme start="20251016142500 +0700" stop="20251016152000 +0700" channel="JKN18">
    <title lang="th">รายการ อาณาจักรสัตว์โลก</title>
    <desc lang="th">-</desc>
  </programme>
  <programme start="20251016152000 +0700" stop="20251016153000 +0700" channel="JKN18">
    <title lang="th">รายการ Anniverse Shop</title>
    <desc lang="th">-</desc>
  </programme>
  <programme start="20251016153000 +0700" stop="20251016162500 +0700" channel="JKN18">
    <title lang="th">รายการ อาณาจักรสัตว์โลก</title>
    <desc lang="th">-</desc>
  </programme>
  <programme start="20251016162500 +0700" stop="20251016165000 +0700" channel="JKN18">
    <title lang="th">รายการ Anniverse Shop</title>
    <desc lang="th">-</desc>
  </programme>
  <programme start="20251016165000 +0700" stop="20251016173500 +0700" channel="JKN18">
    <title lang="th">ซีรีส์อินเดีย ศิวะ อภินิหารตำนานมหาเทพ</title>
    <desc lang="th">-</desc>
  </programme>
  <programme start="20251016173500 +0700" stop="20251016180000 +0700" channel="JKN18">
    <title lang="th">รายการ Anniverse Shop</title>
    <desc lang="th">-</desc>
  </programme>
  <programme start="20251016180000 +0700" stop="20251016180200 +0700" channel="JKN18">
    <title lang="th">เพลงชาติไทย</title>
    <desc lang="th">-</desc>
  </programme>
  <programme start="20251016180200 +0700" stop="20251016185500 +0700" channel="JKN18">
    <title lang="th">รายการ อาณาจักรสัตว์โลก</title>
    <desc lang="th">-</desc>
  </programme>
  <programme start="20251016185500 +0700" stop="20251016190500 +0700" channel="JKN18">
    <title lang="th">รายการ Anniverse Shop</title>
    <desc lang="th">-</desc>
  </programme>
  <programme start="20251016190500 +0700" stop="20251016200000 +0700" channel="JKN18">
    <title lang="th">รายการ อาณาจักรสัตว์โลก</title>
    <desc lang="th">-</desc>
  </programme>
  <programme start="20251016200000 +0700" stop="20251016201500 +0700" channel="JKN18">
    <title lang="th">ข่าวในพระราชสำนัก</title>
    <desc lang="th">-</desc>
  </programme>
  <programme start="20251016201500 +0700" stop="20251016214500 +0700" channel="JKN18">
    <title lang="th">รายการ Hello Anniverse บันเทิง (Live)</title>
    <desc lang="th">-</desc>
  </programme>
  <programme start="20251016214500 +0700" stop="20251016221500 +0700" channel="JKN18">
    <title lang="th">รายการ Hello Anniverse เล่าข่าว (Live)</title>
    <desc lang="th">-</desc>
  </programme>
  <programme start="20251016221500 +0700" stop="20251016233500 +0700" channel="JKN18">
    <title lang="th">ซีรีส์อินเดีย ดงรักภูษาแดง</title>
    <desc lang="th">-</desc>
  </programme>
  <programme start="20251016233500 +0700" stop="20251016235900 +0700" channel="JKN18">
    <title lang="th">รายการ Anniverse Shop</title>
    <desc lang="th">-</desc>
  </programme>
  <programme start="20251016045500 +0700" stop="20251016050000 +0700" channel="NBT">
    <title lang="th">ลีลาชีวิต</title>
    <desc lang="th">-</desc>
  </programme>
  <programme start="20251016050000 +0700" stop="20251016053000 +0700" channel="NBT">
    <title lang="th">พุทธธรรมนำปัญญา</title>
    <desc lang="th">-</desc>
  </programme>
  <programme start="20251016053000 +0700" stop="20251016060000 +0700" channel="NBT">
    <title lang="th">Law เธอมาคุย</title>
    <desc lang="th">-</desc>
  </programme>
  <programme start="20251016060000 +0700" stop="20251016080000 +0700" channel="NBT">
    <title lang="th">ข่าวเช้า NBT News</title>
    <desc lang="th">-</desc>
  </programme>
  <programme start="20251016080000 +0700" stop="20251016080100 +0700" channel="NBT">
    <title lang="th">เคารพธงชาติ</title>
    <desc lang="th">-</desc>
  </programme>
  <programme start="20251016080100 +0700" stop="20251016093000 +0700" channel="NBT">
    <title lang="th">คุยคลายข่าว</title>
    <desc lang="th">-</desc>
  </programme>
  <programme start="20251016093000 +0700" stop="20251016100000 +0700" channel="NBT">
    <title lang="th">สถานีศิริราช</title>
    <desc lang="th">-</desc>
  </programme>
  <programme start="20251016100000 +0700" stop="20251016100500 +0700" channel="NBT">
    <title lang="th">NBT News ข่าวต้นชั่วโมง</title>
    <desc lang="th">-</desc>
  </programme>
  <programme start="20251016100500 +0700" stop="20251016110000 +0700" channel="NBT">
    <title lang="th">Better Future</title>
    <desc lang="th">-</desc>
  </programme>
  <programme start="20251016110000 +0700" stop="20251016110500 +0700" channel="NBT">
    <title lang="th">NBT News ข่าวต้นชั่วโมง</title>
    <desc lang="th">-</desc>
  </programme>
  <programme start="20251016110500 +0700" stop="20251016120000 +0700" channel="NBT">
    <title lang="th">Better Future</title>
    <desc lang="th">-</desc>
  </programme>
  <programme start="20251016120000 +0700" stop="20251016140000 +0700" channel="NBT">
    <title lang="th">ข่าวเที่ยง NBT News</title>
    <desc lang="th">-</desc>
  </programme>
  <programme start="20251016140000 +0700" stop="20251016143000 +0700" channel="NBT">
    <title lang="th">Talkative ไทยแลนด์</title>
    <desc lang="th">-</desc>
  </programme>
  <programme start="20251016143000 +0700" stop="20251016150000 +0700" channel="NBT">
    <title lang="th">เคลียร์คัด ชัดเจน</title>
    <desc lang="th">-</desc>
  </programme>
  <programme start="20251016150000 +0700" stop="20251016150500 +0700" channel="NBT">
    <title lang="th">NBT News ข่าวต้นชั่วโมง</title>
    <desc lang="th">-</desc>
  </programme>
  <programme start="20251016150500 +0700" stop="20251016153000 +0700" channel="NBT">
    <title lang="th">Thailand Connext</title>
    <desc lang="th">-</desc>
  </programme>
  <programme start="20251016153000 +0700" stop="20251016160000 +0700" channel="NBT">
    <title lang="th">NBT มีคำตอบ</title>
    <desc lang="th">-</desc>
  </programme>
  <programme start="20251016160000 +0700" stop="20251016160500 +0700" channel="NBT">
    <title lang="th">NBT News ข่าวต้นชั่วโมง</title>
    <desc lang="th">-</desc>
  </programme>
  <programme start="20251016160500 +0700" stop="20251016170000 +0700" channel="NBT">
    <title lang="th">NBT Documentary สาระดี@เอ็นบีที</title>
    <desc lang="th">-</desc>
  </programme>
  <programme start="20251016170000 +0700" stop="20251016173000 +0700" channel="NBT">
    <title lang="th">NBT ทั่วไทย</title>
    <desc lang="th">-</desc>
  </programme>
  <programme start="20251016173000 +0700" stop="20251016180000 +0700" channel="NBT">
    <title lang="th">ข่าวค่ำ NBT News</title>
    <desc lang="th">-</desc>
  </programme>
  <programme start="20251016180000 +0700" stop="20251016180100 +0700" channel="NBT">
    <title lang="th">เคารพธงชาติ</title>
    <desc lang="th">-</desc>
  </programme>
  <programme start="20251016180100 +0700" stop="20251016200000 +0700" channel="NBT">
    <title lang="th">ข่าวค่ำ NBT News</title>
    <desc lang="th">-</desc>
  </programme>
  <programme start="20251016200000 +0700" stop="20251016202000 +0700" channel="NBT">
    <title lang="th">ข่าวในพระราชสำนัก</title>
    <desc lang="th">-</desc>
  </programme>
  <programme start="20251016202000 +0700" stop="20251016203000 +0700" channel="NBT">
    <title lang="th">คลิป/สารคดีให้ความรู้</title>
    <desc lang="th">-</desc>
  </programme>
  <programme start="20251016203000 +0700" stop="20251016213000 +0700" channel="NBT">
    <title lang="th">เรื่องดังหลังข่าว</title>
    <desc lang="th">-</desc>
  </programme>
  <programme start="20251016213000 +0700" stop="20251016220000 +0700" channel="NBT">
    <title lang="th">NBT World Newsline</title>
    <desc lang="th">-</desc>
  </programme>
  <programme start="20251016220000 +0700" stop="20251016230000 +0700" channel="NBT">
    <title lang="th">NBT Documentary สาระดี@เอ็นบีที</title>
    <desc lang="th">-</desc>
  </programme>
  <programme start="20251016230000 +0700" stop="20251016235900 +0700" channel="NBT">
    <title lang="th">ข่าวดึก NBT News</title>
    <desc lang="th">-</desc>
  </programme>
  <programme start="20251016060000 +0700" stop="20251016061000 +0700" channel="ALTV">
    <title lang="th">???????</title>
    <desc lang="th">-</desc>
  </programme>
  <programme start="20251016061000 +0700" stop="20251016062000 +0700" channel="ALTV">
    <title lang="th">????? ?????????? ??</title>
    <desc lang="th">-</desc>
  </programme>
  <programme start="20251016062000 +0700" stop="20251016062500 +0700" channel="ALTV">
    <title lang="th">???????????</title>
    <desc lang="th">-</desc>
  </programme>
  <programme start="20251016062500 +0700" stop="20251016063000 +0700" channel="ALTV">
    <title lang="th">???? ???? ??? ??????????</title>
    <desc lang="th">-</desc>
  </programme>
  <programme start="20251016063000 +0700" stop="20251016064000 +0700" channel="ALTV">
    <title lang="th">????????????</title>
    <desc lang="th">-</desc>
  </programme>
  <programme start="20251016064000 +0700" stop="20251016070000 +0700" channel="ALTV">
    <title lang="th">????</title>
    <desc lang="th">-</desc>
  </programme>
  <programme start="20251016070000 +0700" stop="20251016073000 +0700" channel="ALTV">
    <title lang="th">??????????????</title>
    <desc lang="th">-</desc>
  </programme>
  <programme start="20251016073000 +0700" stop="20251016080000 +0700" channel="ALTV">
    <title lang="th">?.??? Family</title>
    <desc lang="th">-</desc>
  </programme>
  <programme start="20251016080000 +0700" stop="20251016083000 +0700" channel="ALTV">
    <title lang="th">Talk about kids</title>
    <desc lang="th">-</desc>
  </programme>
  <programme start="20251016083000 +0700" stop="20251016090000 +0700" channel="ALTV">
    <title lang="th">Foodwork</title>
    <desc lang="th">-</desc>
  </programme>
  <programme start="20251016090000 +0700" stop="20251016093000 +0700" channel="ALTV">
    <title lang="th">????????</title>
    <desc lang="th">-</desc>
  </programme>
  <programme start="20251016093000 +0700" stop="20251016100000 +0700" channel="ALTV">
    <title lang="th">???????????</title>
    <desc lang="th">-</desc>
  </programme>
  <programme start="20251016100000 +0700" stop="20251016103000 +0700" channel="ALTV">
    <title lang="th">??????????</title>
    <desc lang="th">-</desc>
  </programme>
  <programme start="20251016103000 +0700" stop="20251016110000 +0700" channel="ALTV">
    <title lang="th">????????????</title>
    <desc lang="th">-</desc>
  </programme>
  <programme start="20251016110000 +0700" stop="20251016130000 +0700" channel="ALTV">
    <title lang="th">????????????</title>
    <desc lang="th">-</desc>
  </programme>
  <programme start="20251016130000 +0700" stop="20251016133000 +0700" channel="ALTV">
    <title lang="th">???????????</title>
    <desc lang="th">-</desc>
  </programme>
  <programme start="20251016133000 +0700" stop="20251016140000 +0700" channel="ALTV">
    <title lang="th">????...??????</title>
    <desc lang="th">-</desc>
  </programme>
  <programme start="20251016140000 +0700" stop="20251016143000 +0700" channel="ALTV">
    <title lang="th">????????</title>
    <desc lang="th">-</desc>
  </programme>
  <programme start="20251016143000 +0700" stop="20251016150000 +0700" channel="ALTV">
    <title lang="th">Come Home ??????????</title>
    <desc lang="th">-</desc>
  </programme>
  <programme start="20251016150000 +0700" stop="20251016153000 +0700" channel="ALTV">
    <title lang="th">????????????</title>
    <desc lang="th">-</desc>
  </programme>
  <programme start="20251016153000 +0700" stop="20251016160000 +0700" channel="ALTV">
    <title lang="th">????????</title>
    <desc lang="th">-</desc>
  </programme>
  <programme start="20251016160000 +0700" stop="20251016161000 +0700" channel="ALTV">
    <title lang="th">Guardian 5 ???????????</title>
    <desc lang="th">-</desc>
  </programme>
  <programme start="20251016161000 +0700" stop="20251016162000 +0700" channel="ALTV">
    <title lang="th">????? ?????????? ??</title>
    <desc lang="th">-</desc>
  </programme>
  <programme start="20251016162000 +0700" stop="20251016163000 +0700" channel="ALTV">
    <title lang="th">?????????????</title>
    <desc lang="th">-</desc>
  </programme>
  <programme start="20251016163000 +0700" stop="20251016164000 +0700" channel="ALTV">
    <title lang="th">Karnimal World 4 ?????????????</title>
    <desc lang="th">-</desc>
  </programme>
  <programme start="20251016164000 +0700" stop="20251016170000 +0700" channel="ALTV">
    <title lang="th">?????????</title>
    <desc lang="th">-</desc>
  </programme>
  <programme start="20251016170000 +0700" stop="20251016171000 +0700" channel="ALTV">
    <title lang="th">Pythagora Switch</title>
    <desc lang="th">-</desc>
  </programme>
  <programme start="20251016171000 +0700" stop="20251016173000 +0700" channel="ALTV">
    <title lang="th">What and Why</title>
    <desc lang="th">-</desc>
  </programme>
  <programme start="20251016173000 +0700" stop="20251016180000 +0700" channel="ALTV">
    <title lang="th">?.??? Family</title>
    <desc lang="th">-</desc>
  </programme>
  <programme start="20251016180000 +0700" stop="20251016190000 +0700" channel="ALTV">
    <title lang="th">Teennovator ??????????</title>
    <desc lang="th">-</desc>
  </programme>
  <programme start="20251016190000 +0700" stop="20251016193000 +0700" channel="ALTV">
    <title lang="th">???????</title>
    <desc lang="th">-</desc>
  </programme>
  <programme start="20251016193000 +0700" stop="20251016203000 +0700" channel="ALTV">
    <title lang="th">You Easy Pass ?????????? ?.1 ?????????</title>
    <desc lang="th">-</desc>
  </programme>
  <programme start="20251016203000 +0700" stop="20251016210000 +0700" channel="ALTV">
    <title lang="th">????????????</title>
    <desc lang="th">-</desc>
  </programme>
  <programme start="20251016210000 +0700" stop="20251016220000 +0700" channel="ALTV">
    <title lang="th">???????????????????</title>
    <desc lang="th">-</desc>
  </programme>
  <programme start="20251016220000 +0700" stop="20251016235900 +0700" channel="ALTV">
    <title lang="th">?????</title>
    <desc lang="th">-</desc>
  </programme>
</tv>
